{
    "bigrams": {
        "neutral": [
            "order number",
            "email address",
            "mobile number",
            "email com",
            "recently purchased",
            "help sarah",
            "number email",
            "name john",
            "john doe",
            "sarah recently"
        ],
        "negative": [
            "order number",
            "email address",
            "email com",
            "customer hold",
            "number email",
            "senior agent",
            "soon possible",
            "anything else",
            "puts customer",
            "working correctly"
        ],
        "positive": [
            "help sarah",
            "order status",
            "order number",
            "wanted confirm",
            "placed order",
            "confirm order",
            "delivery date",
            "status order",
            "agent puts",
            "puts customer"
        ]
    },
    "trigrams": {
        "neutral": [
            "number email address",
            "mobile number email",
            "email address john",
            "doe email com",
            "verify mobile number",
            "johndoe email com",
            "puts customer hold",
            "returns exchanges team",
            "agent puts customer",
            "john doe email"
        ],
        "negative": [
            "puts customer hold",
            "number email address",
            "agent puts customer",
            "address main street",
            "anything else help",
            "email address john",
            "customer hold minutes",
            "order number email",
            "apologize inconvenience caused",
            "mobile number email"
        ],
        "positive": [
            "wanted confirm order",
            "confirm order status",
            "agent puts customer",
            "puts customer hold",
            "estimated delivery date",
            "seller return policy",
            "problem agent puts",
            "sarah help sarah",
            "help sarah day",
            "order status order"
        ]
    }
}